ql/__init__.py
ql/_const.py
ql/_exceptions.py
ql/_http.py
ql/_model.py
ql/_query.py
ql/_types.py
ql/_typing.py
pydantic_graphql-1.2.0.dist-info/METADATA
pydantic_graphql-1.2.0.dist-info/WHEEL
pydantic_graphql-1.2.0.dist-info/RECORD
