Metadata-Version: 2.1
Name: pydantic-graphql
Version: 1.2.0
Summary: non intrusive python graphql client library wrapped around pydantic
Home-page: https://github.com/dsal3389/ql
Keywords: graphql,pydantic,library
Author: daniel sonbolian
Author-email: dsal3389@gmail.com
Requires-Python: >=3.12,<4.0
Classifier: Framework :: Pydantic :: 2
Classifier: Programming Language :: Python :: 3
Classifier: Programming Language :: Python :: 3.12
Classifier: Programming Language :: Python :: 3.13
Classifier: Topic :: Software Development
Classifier: Topic :: Software Development :: Libraries
Classifier: Typing :: Typed
Requires-Dist: pydantic (>=2.8.2,<3.0.0)
Project-URL: Repository, https://github.com/dsal3389/ql
